rspx-0.1.2.dist-info/METADATA
rspx-0.1.2.dist-info/WHEEL
rspx.libs/libgcc_s-5b5488a6.so.1
rspx/__init__.py
rspx/rspx.pypy311-pp73-arm-linux-gnu.so
rspx-0.1.2.dist-info/RECORD
