Metadata-Version: 2.4
Name: rspx
Version: 0.1.2
Classifier: Programming Language :: Rust
Classifier: Programming Language :: Python :: Implementation :: CPython
Classifier: Programming Language :: Python :: Implementation :: PyPy
Requires-Dist: loguru>=0.7.3
Summary: Better Rust Extensions for Python
Author-email: hhglory <hhglory@outlook.com>
Requires-Python: >=3.10
Project-URL: Documentation, https://better-py.github.io/rspx/
Project-URL: Repository, https://github.com/better-py/rspx/
Project-URL: Tracker, https://github.com/better-py/rspx/issues
